hackmenot/__init__.py
hackmenot/__main__.py
hackmenot/cli/__init__.py
hackmenot/cli/git.py
hackmenot/cli/interactive.py
hackmenot/cli/main.py
hackmenot/core/__init__.py
hackmenot/core/cache.py
hackmenot/core/config.py
hackmenot/core/ignores.py
hackmenot/core/models.py
hackmenot/core/regex_cache.py
hackmenot/core/scanner.py
hackmenot/data/__init__.py
hackmenot/data/npm_top50k.txt
hackmenot/data/pypi_top50k.txt
hackmenot/deps/__init__.py
hackmenot/deps/hallucination.py
hackmenot/deps/parser.py
hackmenot/deps/scanner.py
hackmenot/deps/typosquat.py
hackmenot/deps/vulns.py
hackmenot/fixes/__init__.py
hackmenot/fixes/diff.py
hackmenot/fixes/engine.py
hackmenot/fixes/patterns.py
hackmenot/parsers/__init__.py
hackmenot/parsers/base.py
hackmenot/parsers/golang.py
hackmenot/parsers/javascript.py
hackmenot/parsers/python.py
hackmenot/parsers/terraform.py
hackmenot/reporters/__init__.py
hackmenot/reporters/base.py
hackmenot/reporters/markdown.py
hackmenot/reporters/sarif.py
hackmenot/reporters/terminal.py
hackmenot/rules/__init__.py
hackmenot/rules/engine.py
hackmenot/rules/registry.py
hackmenot/rules/builtin/auth/AUTH001.yml
hackmenot/rules/builtin/auth/AUTH002.yml
hackmenot/rules/builtin/auth/AUTH003.yml
hackmenot/rules/builtin/auth/AUTH004.yml
hackmenot/rules/builtin/auth/AUTH005.yml
hackmenot/rules/builtin/auth/AUTH006.yml
hackmenot/rules/builtin/auth/AUTH007.yml
hackmenot/rules/builtin/auth/JSAU001.yml
hackmenot/rules/builtin/auth/JSAU002.yml
hackmenot/rules/builtin/auth/JSAU003.yml
hackmenot/rules/builtin/auth/JSAU004.yml
hackmenot/rules/builtin/crypto/CRYPTO001.yml
hackmenot/rules/builtin/crypto/CRYPTO002.yml
hackmenot/rules/builtin/crypto/CRYPTO003.yml
hackmenot/rules/builtin/crypto/CRYPTO004.yml
hackmenot/rules/builtin/crypto/CRYPTO005.yml
hackmenot/rules/builtin/crypto/CRYPTO006.yml
hackmenot/rules/builtin/crypto/CRYPTO007.yml
hackmenot/rules/builtin/crypto/JSCR001.yml
hackmenot/rules/builtin/crypto/JSCR002.yml
hackmenot/rules/builtin/crypto/JSCR003.yml
hackmenot-1.0.1.dist-info/METADATA
hackmenot-1.0.1.dist-info/WHEEL
hackmenot-1.0.1.dist-info/entry_points.txt
hackmenot-1.0.1.dist-info/licenses/LICENSE
hackmenot-1.0.1.dist-info/RECORD
