Metadata-Version: 2.4
Name: hackmenot
Version: 1.0.1
Summary: AI-Era Code Security Scanner - catches vulnerabilities AI coding assistants introduce
Project-URL: Homepage, https://github.com/b0rd3aux/hackmenot
Project-URL: Repository, https://github.com/b0rd3aux/hackmenot
Project-URL: Documentation, https://github.com/b0rd3aux/hackmenot/tree/main/docs
Project-URL: Issues, https://github.com/b0rd3aux/hackmenot/issues
Author: b0rd3aux
License-Expression: Apache-2.0
License-File: LICENSE
Keywords: ai,claude,code-analysis,copilot,cursor,sast,scanner,security,vulnerability
Classifier: Development Status :: 4 - Beta
Classifier: Environment :: Console
Classifier: Intended Audience :: Developers
Classifier: License :: OSI Approved :: Apache Software License
Classifier: Programming Language :: Python :: 3.10
Classifier: Programming Language :: Python :: 3.11
Classifier: Programming Language :: Python :: 3.12
Classifier: Topic :: Security
Classifier: Topic :: Software Development :: Quality Assurance
Classifier: Topic :: Software Development :: Testing
Requires-Python: >=3.10
Requires-Dist: python-hcl2>=4.3.0
Requires-Dist: pyyaml>=6.0
Requires-Dist: rich>=13.0.0
Requires-Dist: tree-sitter-go>=0.21.0
Requires-Dist: tree-sitter-javascript>=0.23.0
Requires-Dist: tree-sitter>=0.23.0
Requires-Dist: typer>=0.9.0
Provides-Extra: dev
Requires-Dist: mypy>=1.8.0; extra == 'dev'
Requires-Dist: pytest-cov>=4.0.0; extra == 'dev'
Requires-Dist: pytest>=8.0.0; extra == 'dev'
Requires-Dist: ruff>=0.1.0; extra == 'dev'
